biotransformers/__init__.py
biotransformers/bio_transformers.py
biotransformers/version.py
biotransformers/lightning_utils/__init__.py
biotransformers/lightning_utils/data.py
biotransformers/lightning_utils/models.py
biotransformers/lightning_utils/optimizer.py
biotransformers/tests/__init__.py
biotransformers/tests/conftest.py
biotransformers/tests/test_accuracy.py
biotransformers/tests/test_embeddings.py
biotransformers/tests/test_logits.py
biotransformers/tests/test_loglikelihoods.py
biotransformers/tests/test_mutation_score.py
biotransformers/utils/__init__.py
biotransformers/utils/compute_utils.py
biotransformers/utils/constant.py
biotransformers/utils/deprecated.py
biotransformers/utils/logger.py
biotransformers/utils/msa_utils.py
biotransformers/utils/tqdm_utils.py
biotransformers/utils/utils.py
biotransformers/wrappers/__init__.py
biotransformers/wrappers/esm_wrappers.py
biotransformers/wrappers/language_model.py
biotransformers/wrappers/rostlab_wrapper.py
biotransformers/wrappers/transformers_wrappers.py
bio_transformers-0.1.17.dist-info/LICENSE
bio_transformers-0.1.17.dist-info/METADATA
bio_transformers-0.1.17.dist-info/WHEEL
bio_transformers-0.1.17.dist-info/top_level.txt
bio_transformers-0.1.17.dist-info/RECORD
