Metadata-Version: 2.1
Name: bio-transformers
Version: 0.1.17
Summary: Wrapper on top of ESM/Protbert model in order to easily work with protein embedding
Home-page: UNKNOWN
Author: Instadeep
Author-email: a.delfosse@instadeep.com
License: Apache-2.0
Platform: UNKNOWN
Classifier: License :: OSI Approved :: Apache Software License
Classifier: Operating System :: OS Independent
Classifier: Programming Language :: Python :: 3.7
Classifier: Topic :: Scientific/Engineering :: Artificial Intelligence
Classifier: Topic :: Scientific/Engineering :: Bio-Informatics
Classifier: Topic :: Software Development
Requires-Python: >=3.7
License-File: LICENSE
Requires-Dist: biopython (<2,>=1.78)
Requires-Dist: fair-esm (==0.4.0)
Requires-Dist: numpy (<1.19,>=1.16)
Requires-Dist: pandas (>=1.2.3)
Requires-Dist: pytorch-lightning (>=1.3.3)
Requires-Dist: ray (>=1.4.0)
Requires-Dist: scikit-learn (>=0.22.2)
Requires-Dist: torch (<1.9,>=1.7.0)
Requires-Dist: torchmetrics (<0.5,>=0.3.2)
Requires-Dist: tqdm (>=4.60.0)
Requires-Dist: transformers (<4.9,>=4.8)
